botcontrol/__init__.py
botcontrol/adapter.py
botcontrol/alerts.py
botcontrol/context.py
botcontrol/engine.py
botcontrol/permissions.py
botcontrol/scheduler.py
botcontrol/spy.py
botcontrol/storage.py
botcontrol/utils.py
botcontrol/adapter/__init__.py
botcontrol/adapter/base_adapter.py
botcontrol/adapter/rubka_adapter.py
botcontrol/adapter/telegram_adapter.py
botcontrol/examples/simple_bot.py
botcontrol-0.6.0.dist-info/METADATA
botcontrol-0.6.0.dist-info/WHEEL
botcontrol-0.6.0.dist-info/top_level.txt
botcontrol-0.6.0.dist-info/RECORD
