Metadata-Version: 2.4
Name: botcontrol
Version: 0.6.0
Summary: یک فریمورک ربات پیشرفته با Adapterهای لوکال و مدیریت دستورات
Author-email: TM <your.email@example.com>
License: MIT
Project-URL: Homepage, https://github.com/yourusername/botcontrol
Project-URL: Repository, https://github.com/yourusername/botcontrol
Classifier: Programming Language :: Python :: 3.10
Classifier: License :: OSI Approved :: MIT License
Classifier: Operating System :: OS Independent
Requires-Python: >=3.10
